classy_xml/__init__.py
classy_xml/classy_xml.py
classyxml-0.0.6.dist-info/LICENSE
classyxml-0.0.6.dist-info/METADATA
classyxml-0.0.6.dist-info/WHEEL
classyxml-0.0.6.dist-info/top_level.txt
classyxml-0.0.6.dist-info/RECORD
