Metadata-Version: 2.1
Name: classyxml
Version: 0.0.6
Summary: An xml file parser that makes the element text and attributes of an xml file accessible as ClassyXml class attributes.
Home-page: https://github.com/thatdspguy/classy_xml
Author: Keaton Scheible
Author-email: thatdspguy@gmail.com
Project-URL: Bug Tracker, https://github.com/thatdspguy/classy_xml/issues
Classifier: Programming Language :: Python :: 3
Classifier: License :: OSI Approved :: MIT License
Classifier: Operating System :: OS Independent
Requires-Python: >=3.6
License-File: LICENSE
